{
  "AllInPings": 0,
  "AssistMePings": 1,
  "Assists": 12,
  "BaronKills": 0,
  "BasicPings": 0,
  "ChampExperience": 8381,
  "ChampLevel": 11,
  "ChampionID": 89,
  "ChampionName": "Leona",
  "ChampionTransform": 0,
  "CommandPings": 2,
  "ConsumablesPurchased": 8,
  "DamageDealtToBuildings": 93,
  "DamageDealtToObjectives": 589,
  "DamageDealtToTurrets": 93,
  "DamageSelfMitigated": 33701,
  "DangerPings": 0,
  "Deaths": 9,
  "DetectorWardsPlaced": 5,
  "DoubleKills": 0,
  "DragonKills": 0,
  "EligibleForProgression": true,
  "EnemyMissingPings": 6,
  "EnemyVisionPings": 0,
  "FirstBloodAssist": true,
  "FirstBloodKill": false,
  "FirstTowerAssist": false,
  "FirstTowerKill": false,
  "GameEndedInEarlySurrender": false,
  "GameEndedInSurrender": false,
  "GetBackPings": 0,
  "GoldEarned": 7532,
  "GoldSpent": 6925,
  "HoldPings": 0,
  "IndividualPosition": "UTILITY",
  "InhibitorKills": 0,
  "InhibitorTakedowns": 0,
  "InhibitorsLost": 1,
  "Item0": 3876,
  "Item1": 3075,
  "Item2": 3190,
  "Item3": 3111,
  "Item4": 0,
  "Item5": 0,
  "Item6": 3364,
  "ItemsPurchased": 23,
  "KillingSprees": 0,
  "Kills": 2,
  "Lane": "BOTTOM",
  "LargestCriticalStrike": 46,
  "LargestKillingSpree": 0,
  "LargestMultiKill": 1,
  "LongestTimeSpentLiving": 380,
  "MagicDamageDealt": 14586,
  "MagicDamageDealtToChampions": 8731,
  "MagicDamageTaken": 12818,
  "NeedVisionPings": 0,
  "NeutralMinionsKilled": 0,
  "NexusKills": 0,
  "NexusLost": 1,
  "NexusTakedowns": 0,
  "ObjectivesStolen": 0,
  "ObjectivesStolenAssists": 0,
  "OnMyWayPings": 3,
  "ParticipantID": 5,
  "PentaKills": 0,
  "PhysicalDamageDealt": 5594,
  "PhysicalDamageDealtToChampions": 2657,
  "PhysicalDamageTaken": 12271,
  "Placement": 0,
  "PlayerAugment1": 0,
  "PlayerAugment2": 0,
  "PlayerAugment3": 0,
  "PlayerAugment4": 0,
  "PlayerAugment5": 0,
  "PlayerAugment6": 0,
  "PlayerScore0": 0,
  "PlayerScore1": 0,
  "PlayerScore10": 0,
  "PlayerScore11": 0,
  "PlayerScore2": 0,
  "PlayerScore3": 0,
  "PlayerScore4": 0,
  "PlayerScore5": 0,
  "PlayerScore6": 0,
  "PlayerScore7": 0,
  "PlayerScore8": 0,
  "PlayerScore9": 0,
  "PlayerSubteamID": 0,
  "ProfileIcon": 29,
  "PushPings": 0,
  "Puuid": "yPX4Xc7KWZGmGvA-s-clIXo8Cit62aK8R8zJCZ-NNI2TNvmGu4AqweDDizoSf9Cc680cXbj747vcrQ",
  "QuadraKills": 0,
  "RetreatPings": 0,
  "RiotIDGameName": "Pomicard",
  "RiotIDTagline": "2537",
  "Role": "SUPPORT",
  "SightWardsBoughtInGame": 0,
  "Spell1Casts": 48,
  "Spell2Casts": 27,
  "Spell3Casts": 29,
  "Spell4Casts": 8,
  "SubteamPlacement": 0,
  "Summoner1Casts": 4,
  "Summoner1ID": 4,
  "Summoner2Casts": 5,
  "Summoner2ID": 14,
  "SummonerID": "edfhfQDH1AGwvVHU_VpamsL0gQHarXovdUUWK4Gxc3TvMJVjmYx9JrGQiw",
  "SummonerLevel": 35,
  "SummonerName": "Ustmanegadar",
  "TeamEarlySurrendered": false,
  "TeamID": 100,
  "TeamPosition": "UTILITY",
  "TimeCCingOthers": 50,
  "TimePlayed": 1648,
  "TotalAllyJungleMinionsKilled": 0,
  "TotalDamageDealt": 21960,
  "TotalDamageDealtToChampions": 12088,
  "TotalDamageShieldedOnTeammates": 0,
  "TotalDamageTaken": 26125,
  "TotalEnemyJungleMinionsKilled": 0,
  "TotalHeal": 1930,
  "TotalHealsOnTeammates": 240,
  "TotalMinionsKilled": 25,
  "TotalTimeCCDealt": 73,
  "TotalTimeSpentDead": 171,
  "TotalUnitsHealed": 5,
  "TripleKills": 0,
  "TrueDamageDealt": 1779,
  "TrueDamageDealtToChampions": 700,
  "TrueDamageTaken": 1034,
  "TurretKills": 0,
  "TurretTakedowns": 1,
  "TurretsLost": 9,
  "UnrealKills": 0,
  "VisionClearedPings": 0,
  "VisionScore": 63,
  "VisionWardsBoughtInGame": 5,
  "WardsKilled": 10,
  "WardsPlaced": 22,
  "Win": false,
  "challenge_BlastConeOppositeOpponentCount": 0,
  "endOfGameResult": "GameComplete",
  "gameCreation": 1717476059814,
  "gameDuration": 1648,
  "gameEndTimestamp": "2024-06-04 01:08:51",
  "gameId": 5012560066,
  "gameMode": "CLASSIC",
  "gameName": "teambuilder-match-5012560066",
  "gameStartTimestamp": "2024-06-04 00:41:23",
  "gameType": "MATCHED_GAME",
  "gameVersion": "14.11.589.9418",
  "mapId": 11,
  "matchId": "NA1_5012560066",
  "platformId": "NA1"
}
