{
  "AllInPings": 0,
  "AssistMePings": 0,
  "Assists": 0,
  "BaronKills": 0,
  "BasicPings": 0,
  "ChampExperience": 8186,
  "ChampLevel": 11,
  "ChampionID": 164,
  "ChampionName": "Camille",
  "ChampionTransform": 0,
  "CommandPings": 0,
  "ConsumablesPurchased": 1,
  "DamageDealtToBuildings": 0,
  "DamageDealtToObjectives": 0,
  "DamageDealtToTurrets": 0,
  "DamageSelfMitigated": 8373,
  "DangerPings": 0,
  "Deaths": 3,
  "DetectorWardsPlaced": 0,
  "DoubleKills": 0,
  "DragonKills": 0,
  "EligibleForProgression": true,
  "EnemyMissingPings": 0,
  "EnemyVisionPings": 0,
  "FirstBloodAssist": false,
  "FirstBloodKill": false,
  "FirstTowerAssist": false,
  "FirstTowerKill": false,
  "GameEndedInEarlySurrender": false,
  "GameEndedInSurrender": true,
  "GetBackPings": 0,
  "GoldEarned": 5173,
  "GoldSpent": 5033,
  "HoldPings": 0,
  "IndividualPosition": "TOP",
  "InhibitorKills": 0,
  "InhibitorTakedowns": 0,
  "InhibitorsLost": 1,
  "Item0": 3078,
  "Item1": 1036,
  "Item2": 2031,
  "Item3": 1036,
  "Item4": 1036,
  "Item5": 1055,
  "Item6": 3340,
  "ItemsPurchased": 12,
  "KillingSprees": 0,
  "Kills": 0,
  "Lane": "TOP",
  "LargestCriticalStrike": 0,
  "LargestKillingSpree": 0,
  "LargestMultiKill": 0,
  "LongestTimeSpentLiving": 389,
  "MagicDamageDealt": 25,
  "MagicDamageDealtToChampions": 25,
  "MagicDamageTaken": 817,
  "NeedVisionPings": 0,
  "NeutralMinionsKilled": 0,
  "NexusKills": 0,
  "NexusLost": 0,
  "NexusTakedowns": 0,
  "ObjectivesStolen": 0,
  "ObjectivesStolenAssists": 0,
  "OnMyWayPings": 0,
  "ParticipantID": 1,
  "PentaKills": 0,
  "PhysicalDamageDealt": 31475,
  "PhysicalDamageDealtToChampions": 4619,
  "PhysicalDamageTaken": 8536,
  "Placement": 0,
  "PlayerAugment1": 0,
  "PlayerAugment2": 0,
  "PlayerAugment3": 0,
  "PlayerAugment4": 0,
  "PlayerAugment5": 0,
  "PlayerAugment6": 0,
  "PlayerScore0": 0,
  "PlayerScore1": 0,
  "PlayerScore10": 0,
  "PlayerScore11": 0,
  "PlayerScore2": 0,
  "PlayerScore3": 0,
  "PlayerScore4": 0,
  "PlayerScore5": 0,
  "PlayerScore6": 0,
  "PlayerScore7": 0,
  "PlayerScore8": 0,
  "PlayerScore9": 0,
  "PlayerSubteamID": 0,
  "ProfileIcon": 4540,
  "PushPings": 0,
  "Puuid": "z5QocchfjwqbxwtMhj8dgeLpQ6ekww6HZA3yhZon0bHldhIs_EjvUXcqdKtmEYit43Z2sGagZSjj1g",
  "QuadraKills": 0,
  "RetreatPings": 0,
  "RiotIDGameName": "BlaoThorne RJ",
  "RiotIDTagline": "小自闭원우",
  "Role": "SOLO",
  "SightWardsBoughtInGame": 0,
  "Spell1Casts": 87,
  "Spell2Casts": 20,
  "Spell3Casts": 32,
  "Spell4Casts": 1,
  "SubteamPlacement": 0,
  "Summoner1Casts": 2,
  "Summoner1ID": 14,
  "Summoner2Casts": 0,
  "Summoner2ID": 21,
  "SummonerID": "yVuhAF9d3dmjyoZtKxDjAF5WdWvlZwYXxKsnaToMgnQ0qf8",
  "SummonerLevel": 3044,
  "SummonerName": "BlaoThorne RJ",
  "TeamEarlySurrendered": false,
  "TeamID": 100,
  "TeamPosition": "TOP",
  "TimeCCingOthers": 5,
  "TimePlayed": 1203,
  "TotalAllyJungleMinionsKilled": 0,
  "TotalDamageDealt": 42142,
  "TotalDamageDealtToChampions": 5865,
  "TotalDamageShieldedOnTeammates": 0,
  "TotalDamageTaken": 10233,
  "TotalEnemyJungleMinionsKilled": 0,
  "TotalHeal": 1261,
  "TotalHealsOnTeammates": 0,
  "TotalMinionsKilled": 106,
  "TotalTimeCCDealt": 63,
  "TotalTimeSpentDead": 68,
  "TotalUnitsHealed": 1,
  "TripleKills": 0,
  "TrueDamageDealt": 10642,
  "TrueDamageDealtToChampions": 1220,
  "TrueDamageTaken": 879,
  "TurretKills": 0,
  "TurretTakedowns": 0,
  "TurretsLost": 6,
  "UnrealKills": 0,
  "VisionClearedPings": 0,
  "VisionScore": 6,
  "VisionWardsBoughtInGame": 0,
  "WardsKilled": 0,
  "WardsPlaced": 4,
  "Win": false,
  "challenge_BlastConeOppositeOpponentCount": 0,
  "endOfGameResult": "GameComplete",
  "gameCreation": 1719972990121,
  "gameDuration": 1203,
  "gameEndTimestamp": "2024-07-02 22:37:16",
  "gameId": 5031926592,
  "gameMode": "CLASSIC",
  "gameName": "teambuilder-match-5031926592",
  "gameStartTimestamp": "2024-07-02 22:17:13",
  "gameType": "MATCHED_GAME",
  "gameVersion": "14.13.598.9749",
  "mapId": 11,
  "matchId": "NA1_5031926592",
  "platformId": "NA1"
}
