{
  "AllInPings": 0,
  "AssistMePings": 1,
  "Assists": 7,
  "BaronKills": 0,
  "BasicPings": 0,
  "ChampExperience": 12894,
  "ChampLevel": 14,
  "ChampionID": 76,
  "ChampionName": "Nidalee",
  "ChampionTransform": 0,
  "CommandPings": 2,
  "ConsumablesPurchased": 3,
  "DamageDealtToBuildings": 8,
  "DamageDealtToObjectives": 26496,
  "DamageDealtToTurrets": 8,
  "DamageSelfMitigated": 15941,
  "DangerPings": 0,
  "Deaths": 6,
  "DetectorWardsPlaced": 1,
  "DoubleKills": 0,
  "DragonKills": 1,
  "EligibleForProgression": true,
  "EnemyMissingPings": 6,
  "EnemyVisionPings": 2,
  "FirstBloodAssist": false,
  "FirstBloodKill": false,
  "FirstTowerAssist": false,
  "FirstTowerKill": false,
  "GameEndedInEarlySurrender": false,
  "GameEndedInSurrender": true,
  "GetBackPings": 3,
  "GoldEarned": 10947,
  "GoldSpent": 9875,
  "HoldPings": 0,
  "IndividualPosition": "JUNGLE",
  "InhibitorKills": 0,
  "InhibitorTakedowns": 0,
  "InhibitorsLost": 1,
  "Item0": 3100,
  "Item1": 6653,
  "Item2": 1058,
  "Item3": 3020,
  "Item4": 1052,
  "Item5": 1082,
  "Item6": 3364,
  "ItemsPurchased": 24,
  "KillingSprees": 2,
  "Kills": 6,
  "Lane": "JUNGLE",
  "LargestCriticalStrike": 0,
  "LargestKillingSpree": 2,
  "LargestMultiKill": 1,
  "LongestTimeSpentLiving": 569,
  "MagicDamageDealt": 141146,
  "MagicDamageDealtToChampions": 10588,
  "MagicDamageTaken": 6098,
  "NeedVisionPings": 0,
  "NeutralMinionsKilled": 153,
  "NexusKills": 0,
  "NexusLost": 0,
  "NexusTakedowns": 0,
  "ObjectivesStolen": 0,
  "ObjectivesStolenAssists": 0,
  "OnMyWayPings": 37,
  "ParticipantID": 7,
  "PentaKills": 0,
  "PhysicalDamageDealt": 16797,
  "PhysicalDamageDealtToChampions": 1193,
  "PhysicalDamageTaken": 26019,
  "Placement": 0,
  "PlayerAugment1": 0,
  "PlayerAugment2": 0,
  "PlayerAugment3": 0,
  "PlayerAugment4": 0,
  "PlayerAugment5": 0,
  "PlayerAugment6": 0,
  "PlayerScore0": 0,
  "PlayerScore1": 0,
  "PlayerScore10": 0,
  "PlayerScore11": 0,
  "PlayerScore2": 0,
  "PlayerScore3": 0,
  "PlayerScore4": 0,
  "PlayerScore5": 0,
  "PlayerScore6": 0,
  "PlayerScore7": 0,
  "PlayerScore8": 0,
  "PlayerScore9": 0,
  "PlayerSubteamID": 0,
  "ProfileIcon": 5768,
  "PushPings": 1,
  "Puuid": "la2uXIktQ3uKbGIXoE3M-EYPXHRf5rEfLmRwtt9lT-xcdAkKLUjxjvZXCD8mXUB6Iq1A_j3hb4uMgQ",
  "QuadraKills": 0,
  "RetreatPings": 0,
  "RiotIDGameName": "Carmen Anthony",
  "RiotIDTagline": "JAW",
  "Role": "NONE",
  "SightWardsBoughtInGame": 0,
  "Spell1Casts": 321,
  "Spell2Casts": 236,
  "Spell3Casts": 132,
  "Spell4Casts": 287,
  "SubteamPlacement": 0,
  "Summoner1Casts": 4,
  "Summoner1ID": 4,
  "Summoner2Casts": 17,
  "Summoner2ID": 11,
  "SummonerID": "apsH1jK5Q39rab3wuedGDn-kh5okDpPMckE_iZ6mRVZ9pxE",
  "SummonerLevel": 96,
  "SummonerName": "Larry Joe Bird ",
  "TeamEarlySurrendered": false,
  "TeamID": 200,
  "TeamPosition": "JUNGLE",
  "TimeCCingOthers": 6,
  "TimePlayed": 1700,
  "TotalAllyJungleMinionsKilled": 120,
  "TotalDamageDealt": 226184,
  "TotalDamageDealtToChampions": 13095,
  "TotalDamageShieldedOnTeammates": 0,
  "TotalDamageTaken": 33926,
  "TotalEnemyJungleMinionsKilled": 0,
  "TotalHeal": 21826,
  "TotalHealsOnTeammates": 4186,
  "TotalMinionsKilled": 15,
  "TotalTimeCCDealt": 116,
  "TotalTimeSpentDead": 127,
  "TotalUnitsHealed": 5,
  "TripleKills": 0,
  "TrueDamageDealt": 68241,
  "TrueDamageDealtToChampions": 1313,
  "TrueDamageTaken": 1808,
  "TurretKills": 0,
  "TurretTakedowns": 0,
  "TurretsLost": 6,
  "UnrealKills": 0,
  "VisionClearedPings": 0,
  "VisionScore": 23,
  "VisionWardsBoughtInGame": 1,
  "WardsKilled": 1,
  "WardsPlaced": 8,
  "Win": false,
  "challenge_BlastConeOppositeOpponentCount": 0,
  "endOfGameResult": "GameComplete",
  "gameCreation": 1728493069986,
  "gameDuration": 1700,
  "gameEndTimestamp": "2024-10-09 13:27:32",
  "gameId": 5129883863,
  "gameMode": "CLASSIC",
  "gameName": "teambuilder-match-5129883863",
  "gameStartTimestamp": "2024-10-09 12:59:13",
  "gameType": "MATCHED_GAME",
  "gameVersion": "14.20.623.6777",
  "mapId": 11,
  "matchId": "NA1_5129883863",
  "platformId": "NA1"
}
