{
  "AllInPings": 0,
  "AssistMePings": 1,
  "Assists": 4,
  "BaronKills": 0,
  "BasicPings": 0,
  "ChampExperience": 15973,
  "ChampLevel": 16,
  "ChampionID": 8,
  "ChampionName": "Vladimir",
  "ChampionTransform": 0,
  "CommandPings": 2,
  "ConsumablesPurchased": 2,
  "DamageDealtToBuildings": 1859,
  "DamageDealtToObjectives": 3068,
  "DamageDealtToTurrets": 1859,
  "DamageSelfMitigated": 14458,
  "DangerPings": 0,
  "Deaths": 5,
  "DetectorWardsPlaced": 0,
  "DoubleKills": 0,
  "DragonKills": 0,
  "EligibleForProgression": true,
  "EnemyMissingPings": 7,
  "EnemyVisionPings": 0,
  "FirstBloodAssist": false,
  "FirstBloodKill": false,
  "FirstTowerAssist": false,
  "FirstTowerKill": false,
  "GameEndedInEarlySurrender": false,
  "GameEndedInSurrender": false,
  "GetBackPings": 0,
  "GoldEarned": 12239,
  "GoldSpent": 11300,
  "HoldPings": 0,
  "IndividualPosition": "MIDDLE",
  "InhibitorKills": 0,
  "InhibitorTakedowns": 0,
  "InhibitorsLost": 2,
  "Item0": 3137,
  "Item1": 3089,
  "Item2": 1082,
  "Item3": 3020,
  "Item4": 4646,
  "Item5": 0,
  "Item6": 3340,
  "ItemsPurchased": 16,
  "KillingSprees": 2,
  "Kills": 5,
  "Lane": "MIDDLE",
  "LargestCriticalStrike": 0,
  "LargestKillingSpree": 2,
  "LargestMultiKill": 1,
  "LongestTimeSpentLiving": 884,
  "MagicDamageDealt": 162708,
  "MagicDamageDealtToChampions": 26894,
  "MagicDamageTaken": 10776,
  "NeedVisionPings": 0,
  "NeutralMinionsKilled": 0,
  "NexusKills": 0,
  "NexusLost": 1,
  "NexusTakedowns": 0,
  "ObjectivesStolen": 0,
  "ObjectivesStolenAssists": 0,
  "OnMyWayPings": 3,
  "ParticipantID": 3,
  "PentaKills": 0,
  "PhysicalDamageDealt": 13138,
  "PhysicalDamageDealtToChampions": 691,
  "PhysicalDamageTaken": 15543,
  "Placement": 0,
  "PlayerAugment1": 0,
  "PlayerAugment2": 0,
  "PlayerAugment3": 0,
  "PlayerAugment4": 0,
  "PlayerAugment5": 0,
  "PlayerAugment6": 0,
  "PlayerScore0": 0,
  "PlayerScore1": 0,
  "PlayerScore10": 0,
  "PlayerScore11": 0,
  "PlayerScore2": 0,
  "PlayerScore3": 0,
  "PlayerScore4": 0,
  "PlayerScore5": 0,
  "PlayerScore6": 0,
  "PlayerScore7": 0,
  "PlayerScore8": 0,
  "PlayerScore9": 0,
  "PlayerSubteamID": 0,
  "ProfileIcon": 5370,
  "PushPings": 0,
  "Puuid": "Y8QX5vk7a9mbfScLGmagem_pb5iDZhEwNk3_Ot5fFvPAsRI46N9tuvz7zy3aftxjnPBBex8WVqMKzA",
  "QuadraKills": 0,
  "RetreatPings": 0,
  "RiotIDGameName": "Spanther10",
  "RiotIDTagline": "NA1",
  "Role": "SOLO",
  "SightWardsBoughtInGame": 0,
  "Spell1Casts": 222,
  "Spell2Casts": 9,
  "Spell3Casts": 82,
  "Spell4Casts": 9,
  "SubteamPlacement": 0,
  "Summoner1Casts": 4,
  "Summoner1ID": 4,
  "Summoner2Casts": 5,
  "Summoner2ID": 14,
  "SummonerID": "svs2fqWc07rJfJaxI63xktMV_hdV58w9yYgmAkLbRXyuTSI",
  "SummonerLevel": 531,
  "SummonerName": "Spanther10",
  "TeamEarlySurrendered": false,
  "TeamID": 100,
  "TeamPosition": "MIDDLE",
  "TimeCCingOthers": 2,
  "TimePlayed": 1738,
  "TotalAllyJungleMinionsKilled": 0,
  "TotalDamageDealt": 177460,
  "TotalDamageDealtToChampions": 28616,
  "TotalDamageShieldedOnTeammates": 0,
  "TotalDamageTaken": 29338,
  "TotalEnemyJungleMinionsKilled": 0,
  "TotalHeal": 23414,
  "TotalHealsOnTeammates": 0,
  "TotalMinionsKilled": 257,
  "TotalTimeCCDealt": 50,
  "TotalTimeSpentDead": 178,
  "TotalUnitsHealed": 1,
  "TripleKills": 0,
  "TrueDamageDealt": 1613,
  "TrueDamageDealtToChampions": 1031,
  "TrueDamageTaken": 3018,
  "TurretKills": 0,
  "TurretTakedowns": 1,
  "TurretsLost": 11,
  "UnrealKills": 0,
  "VisionClearedPings": 0,
  "VisionScore": 14,
  "VisionWardsBoughtInGame": 0,
  "WardsKilled": 2,
  "WardsPlaced": 7,
  "Win": false,
  "challenge_BlastConeOppositeOpponentCount": 0,
  "endOfGameResult": "GameComplete",
  "gameCreation": 1718761072819,
  "gameDuration": 1738,
  "gameEndTimestamp": "2024-06-18 22:07:07",
  "gameId": 5022798859,
  "gameMode": "CLASSIC",
  "gameName": "teambuilder-match-5022798859",
  "gameStartTimestamp": "2024-06-18 21:38:09",
  "gameType": "MATCHED_GAME",
  "gameVersion": "14.12.594.4901",
  "mapId": 11,
  "matchId": "NA1_5022798859",
  "platformId": "NA1"
}
