{
  "AllInPings": 0,
  "AssistMePings": 1,
  "Assists": 22,
  "BaronKills": 0,
  "BasicPings": 0,
  "ChampExperience": 10630,
  "ChampLevel": 13,
  "ChampionID": 89,
  "ChampionName": "Leona",
  "ChampionTransform": 0,
  "CommandPings": 1,
  "ConsumablesPurchased": 8,
  "DamageDealtToBuildings": 320,
  "DamageDealtToObjectives": 542,
  "DamageDealtToTurrets": 320,
  "DamageSelfMitigated": 23593,
  "DangerPings": 0,
  "Deaths": 4,
  "DetectorWardsPlaced": 6,
  "DoubleKills": 0,
  "DragonKills": 0,
  "EligibleForProgression": true,
  "EnemyMissingPings": 4,
  "EnemyVisionPings": 1,
  "FirstBloodAssist": false,
  "FirstBloodKill": false,
  "FirstTowerAssist": false,
  "FirstTowerKill": false,
  "GameEndedInEarlySurrender": false,
  "GameEndedInSurrender": false,
  "GetBackPings": 0,
  "GoldEarned": 8178,
  "GoldSpent": 6250,
  "HoldPings": 0,
  "IndividualPosition": "UTILITY",
  "InhibitorKills": 0,
  "InhibitorTakedowns": 1,
  "InhibitorsLost": 0,
  "Item0": 3190,
  "Item1": 3109,
  "Item2": 3877,
  "Item3": 0,
  "Item4": 0,
  "Item5": 3009,
  "Item6": 3364,
  "ItemsPurchased": 25,
  "KillingSprees": 0,
  "Kills": 1,
  "Lane": "BOTTOM",
  "LargestCriticalStrike": 0,
  "LargestKillingSpree": 0,
  "LargestMultiKill": 1,
  "LongestTimeSpentLiving": 715,
  "MagicDamageDealt": 11227,
  "MagicDamageDealtToChampions": 8249,
  "MagicDamageTaken": 8609,
  "NeedVisionPings": 0,
  "NeutralMinionsKilled": 0,
  "NexusKills": 0,
  "NexusLost": 0,
  "NexusTakedowns": 1,
  "ObjectivesStolen": 0,
  "ObjectivesStolenAssists": 0,
  "OnMyWayPings": 5,
  "ParticipantID": 5,
  "PentaKills": 0,
  "PhysicalDamageDealt": 7000,
  "PhysicalDamageDealtToChampions": 5018,
  "PhysicalDamageTaken": 10842,
  "Placement": 0,
  "PlayerAugment1": 0,
  "PlayerAugment2": 0,
  "PlayerAugment3": 0,
  "PlayerAugment4": 0,
  "PlayerAugment5": 0,
  "PlayerAugment6": 0,
  "PlayerScore0": 0,
  "PlayerScore1": 0,
  "PlayerScore10": 0,
  "PlayerScore11": 0,
  "PlayerScore2": 0,
  "PlayerScore3": 0,
  "PlayerScore4": 0,
  "PlayerScore5": 0,
  "PlayerScore6": 0,
  "PlayerScore7": 0,
  "PlayerScore8": 0,
  "PlayerScore9": 0,
  "PlayerSubteamID": 0,
  "ProfileIcon": 3378,
  "PushPings": 0,
  "Puuid": "tRHWsd373IksboQfmojUTjH4V0eMcx5sbZ7kA8eb3NtkQkhfLRmrNoUPJCUdnj9aV1UzSQ1gV-yGKw",
  "QuadraKills": 0,
  "RetreatPings": 0,
  "RiotIDGameName": "Counterflow",
  "RiotIDTagline": "NA1",
  "Role": "SUPPORT",
  "SightWardsBoughtInGame": 0,
  "Spell1Casts": 44,
  "Spell2Casts": 43,
  "Spell3Casts": 33,
  "Spell4Casts": 11,
  "SubteamPlacement": 0,
  "Summoner1Casts": 9,
  "Summoner1ID": 4,
  "Summoner2Casts": 7,
  "Summoner2ID": 14,
  "SummonerID": "BN2KX5G8SRLpzrms8dzZefWPkJKuYjb5uqiEwhkNLAytyQk",
  "SummonerLevel": 314,
  "SummonerName": "Counterflow",
  "TeamEarlySurrendered": false,
  "TeamID": 100,
  "TeamPosition": "UTILITY",
  "TimeCCingOthers": 53,
  "TimePlayed": 1616,
  "TotalAllyJungleMinionsKilled": 0,
  "TotalDamageDealt": 20566,
  "TotalDamageDealtToChampions": 14226,
  "TotalDamageShieldedOnTeammates": 411,
  "TotalDamageTaken": 20387,
  "TotalEnemyJungleMinionsKilled": 0,
  "TotalHeal": 1614,
  "TotalHealsOnTeammates": 345,
  "TotalMinionsKilled": 21,
  "TotalTimeCCDealt": 71,
  "TotalTimeSpentDead": 87,
  "TotalUnitsHealed": 5,
  "TripleKills": 0,
  "TrueDamageDealt": 2339,
  "TrueDamageDealtToChampions": 958,
  "TrueDamageTaken": 935,
  "TurretKills": 0,
  "TurretTakedowns": 3,
  "TurretsLost": 3,
  "UnrealKills": 0,
  "VisionClearedPings": 0,
  "VisionScore": 68,
  "VisionWardsBoughtInGame": 6,
  "WardsKilled": 7,
  "WardsPlaced": 33,
  "Win": true,
  "challenge_BlastConeOppositeOpponentCount": 0,
  "endOfGameResult": "GameComplete",
  "gameCreation": 1717293179961,
  "gameDuration": 1616,
  "gameEndTimestamp": "2024-06-01 22:20:16",
  "gameId": 5010904844,
  "gameMode": "CLASSIC",
  "gameName": "teambuilder-match-5010904844",
  "gameStartTimestamp": "2024-06-01 21:53:19",
  "gameType": "MATCHED_GAME",
  "gameVersion": "14.11.589.9418",
  "mapId": 11,
  "matchId": "NA1_5010904844",
  "platformId": "NA1"
}
