{
  "AllInPings": 0,
  "AssistMePings": 0,
  "Assists": 9,
  "BaronKills": 0,
  "BasicPings": 0,
  "ChampExperience": 9865,
  "ChampLevel": 12,
  "ChampionID": 235,
  "ChampionName": "Senna",
  "ChampionTransform": 0,
  "CommandPings": 2,
  "ConsumablesPurchased": 8,
  "DamageDealtToBuildings": 303,
  "DamageDealtToObjectives": 422,
  "DamageDealtToTurrets": 303,
  "DamageSelfMitigated": 5705,
  "DangerPings": 0,
  "Deaths": 8,
  "DetectorWardsPlaced": 4,
  "DoubleKills": 0,
  "DragonKills": 0,
  "EligibleForProgression": true,
  "EnemyMissingPings": 0,
  "EnemyVisionPings": 1,
  "FirstBloodAssist": false,
  "FirstBloodKill": false,
  "FirstTowerAssist": false,
  "FirstTowerKill": false,
  "GameEndedInEarlySurrender": false,
  "GameEndedInSurrender": false,
  "GetBackPings": 0,
  "GoldEarned": 7936,
  "GoldSpent": 7575,
  "HoldPings": 0,
  "IndividualPosition": "UTILITY",
  "InhibitorKills": 0,
  "InhibitorTakedowns": 0,
  "InhibitorsLost": 3,
  "Item0": 3870,
  "Item1": 3009,
  "Item2": 6620,
  "Item3": 3071,
  "Item4": 2055,
  "Item5": 0,
  "Item6": 3364,
  "ItemsPurchased": 26,
  "KillingSprees": 0,
  "Kills": 2,
  "Lane": "BOTTOM",
  "LargestCriticalStrike": 379,
  "LargestKillingSpree": 0,
  "LargestMultiKill": 1,
  "LongestTimeSpentLiving": 508,
  "MagicDamageDealt": 663,
  "MagicDamageDealtToChampions": 663,
  "MagicDamageTaken": 5157,
  "NeedVisionPings": 0,
  "NeutralMinionsKilled": 0,
  "NexusKills": 0,
  "NexusLost": 1,
  "NexusTakedowns": 0,
  "ObjectivesStolen": 0,
  "ObjectivesStolenAssists": 1,
  "OnMyWayPings": 1,
  "ParticipantID": 10,
  "PentaKills": 0,
  "PhysicalDamageDealt": 25835,
  "PhysicalDamageDealtToChampions": 12125,
  "PhysicalDamageTaken": 16628,
  "Placement": 0,
  "PlayerAugment1": 0,
  "PlayerAugment2": 0,
  "PlayerAugment3": 0,
  "PlayerAugment4": 0,
  "PlayerAugment5": 0,
  "PlayerAugment6": 0,
  "PlayerScore0": 0,
  "PlayerScore1": 0,
  "PlayerScore10": 0,
  "PlayerScore11": 0,
  "PlayerScore2": 0,
  "PlayerScore3": 0,
  "PlayerScore4": 0,
  "PlayerScore5": 0,
  "PlayerScore6": 0,
  "PlayerScore7": 0,
  "PlayerScore8": 0,
  "PlayerScore9": 0,
  "PlayerSubteamID": 0,
  "ProfileIcon": 6623,
  "PushPings": 0,
  "Puuid": "0o-iSaCAdqWS5DklzB1V7TF8lPmItfZb5WoVBL45mZNFjT6rX4og5h03PkaTw8DbiJZ6lbMuiSWX0Q",
  "QuadraKills": 0,
  "RetreatPings": 0,
  "RiotIDGameName": "abigbroomstick",
  "RiotIDTagline": "NA1",
  "Role": "SUPPORT",
  "SightWardsBoughtInGame": 0,
  "Spell1Casts": 62,
  "Spell2Casts": 34,
  "Spell3Casts": 20,
  "Spell4Casts": 5,
  "SubteamPlacement": 0,
  "Summoner1Casts": 2,
  "Summoner1ID": 4,
  "Summoner2Casts": 3,
  "Summoner2ID": 7,
  "SummonerID": "8ramVx5miID4TFmgAvSp8Ts_3c8UoWuEAeFbs2mfGViyKq8",
  "SummonerLevel": 436,
  "SummonerName": "abigbroomstick",
  "TeamEarlySurrendered": false,
  "TeamID": 200,
  "TeamPosition": "UTILITY",
  "TimeCCingOthers": 48,
  "TimePlayed": 1568,
  "TotalAllyJungleMinionsKilled": 0,
  "TotalDamageDealt": 27262,
  "TotalDamageDealtToChampions": 12788,
  "TotalDamageShieldedOnTeammates": 1096,
  "TotalDamageTaken": 22280,
  "TotalEnemyJungleMinionsKilled": 0,
  "TotalHeal": 8656,
  "TotalHealsOnTeammates": 4180,
  "TotalMinionsKilled": 27,
  "TotalTimeCCDealt": 173,
  "TotalTimeSpentDead": 195,
  "TotalUnitsHealed": 5,
  "TripleKills": 0,
  "TrueDamageDealt": 763,
  "TrueDamageDealtToChampions": 0,
  "TrueDamageTaken": 494,
  "TurretKills": 0,
  "TurretTakedowns": 0,
  "TurretsLost": 11,
  "UnrealKills": 0,
  "VisionClearedPings": 0,
  "VisionScore": 47,
  "VisionWardsBoughtInGame": 5,
  "WardsKilled": 6,
  "WardsPlaced": 22,
  "Win": false,
  "challenge_BlastConeOppositeOpponentCount": 0,
  "endOfGameResult": "GameComplete",
  "gameCreation": 1723935143321,
  "gameDuration": 1568,
  "gameEndTimestamp": "2024-08-17 19:18:54",
  "gameId": 5088657549,
  "gameMode": "CLASSIC",
  "gameName": "teambuilder-match-5088657549",
  "gameStartTimestamp": "2024-08-17 18:52:45",
  "gameType": "MATCHED_GAME",
  "gameVersion": "14.16.609.8277",
  "mapId": 11,
  "matchId": "NA1_5088657549",
  "platformId": "NA1"
}
