{
  "AllInPings": 0,
  "AssistMePings": 0,
  "Assists": 1,
  "BaronKills": 0,
  "BasicPings": 0,
  "ChampExperience": 5805,
  "ChampLevel": 9,
  "ChampionID": 18,
  "ChampionName": "Tristana",
  "ChampionTransform": 0,
  "CommandPings": 1,
  "ConsumablesPurchased": 2,
  "DamageDealtToBuildings": 2224,
  "DamageDealtToObjectives": 3823,
  "DamageDealtToTurrets": 2224,
  "DamageSelfMitigated": 4706,
  "DangerPings": 0,
  "Deaths": 4,
  "DetectorWardsPlaced": 0,
  "DoubleKills": 0,
  "DragonKills": 0,
  "EligibleForProgression": true,
  "EnemyMissingPings": 1,
  "EnemyVisionPings": 0,
  "FirstBloodAssist": false,
  "FirstBloodKill": false,
  "FirstTowerAssist": false,
  "FirstTowerKill": false,
  "GameEndedInEarlySurrender": false,
  "GameEndedInSurrender": true,
  "GetBackPings": 1,
  "GoldEarned": 6310,
  "GoldSpent": 5950,
  "HoldPings": 0,
  "IndividualPosition": "BOTTOM",
  "InhibitorKills": 0,
  "InhibitorTakedowns": 0,
  "InhibitorsLost": 1,
  "Item0": 1055,
  "Item1": 3031,
  "Item2": 3006,
  "Item3": 1018,
  "Item4": 1042,
  "Item5": 0,
  "Item6": 3363,
  "ItemsPurchased": 14,
  "KillingSprees": 0,
  "Kills": 2,
  "Lane": "NONE",
  "LargestCriticalStrike": 385,
  "LargestKillingSpree": 0,
  "LargestMultiKill": 1,
  "LongestTimeSpentLiving": 404,
  "MagicDamageDealt": 12989,
  "MagicDamageDealtToChampions": 1154,
  "MagicDamageTaken": 2898,
  "NeedVisionPings": 0,
  "NeutralMinionsKilled": 0,
  "NexusKills": 0,
  "NexusLost": 0,
  "NexusTakedowns": 0,
  "ObjectivesStolen": 0,
  "ObjectivesStolenAssists": 0,
  "OnMyWayPings": 3,
  "ParticipantID": 9,
  "PentaKills": 0,
  "PhysicalDamageDealt": 37294,
  "PhysicalDamageDealtToChampions": 6057,
  "PhysicalDamageTaken": 8243,
  "Placement": 0,
  "PlayerAugment1": 0,
  "PlayerAugment2": 0,
  "PlayerAugment3": 0,
  "PlayerAugment4": 0,
  "PlayerAugment5": 0,
  "PlayerAugment6": 0,
  "PlayerScore0": 0,
  "PlayerScore1": 0,
  "PlayerScore10": 0,
  "PlayerScore11": 0,
  "PlayerScore2": 0,
  "PlayerScore3": 0,
  "PlayerScore4": 0,
  "PlayerScore5": 0,
  "PlayerScore6": 0,
  "PlayerScore7": 0,
  "PlayerScore8": 0,
  "PlayerScore9": 0,
  "PlayerSubteamID": 0,
  "ProfileIcon": 6549,
  "PushPings": 0,
  "Puuid": "_Euk4V_SeG4RM_O4f5LBFwyI94ZXG5TvSwnGNZ0QfSle8a_tIS4xHmnR0pp9I0jp_AY1pT4sDJkxZg",
  "QuadraKills": 0,
  "RetreatPings": 0,
  "RiotIDGameName": "Sneaky",
  "RiotIDTagline": "NA69",
  "Role": "DUO",
  "SightWardsBoughtInGame": 0,
  "Spell1Casts": 24,
  "Spell2Casts": 19,
  "Spell3Casts": 16,
  "Spell4Casts": 3,
  "SubteamPlacement": 0,
  "Summoner1Casts": 2,
  "Summoner1ID": 4,
  "Summoner2Casts": 3,
  "Summoner2ID": 7,
  "SummonerID": "qND6_aOxYhh63PSRr4kMXU87LdzfQmcFoCo2V7b94jo",
  "SummonerLevel": 660,
  "SummonerName": "SentientAI",
  "TeamEarlySurrendered": false,
  "TeamID": 200,
  "TeamPosition": "BOTTOM",
  "TimeCCingOthers": 2,
  "TimePlayed": 932,
  "TotalAllyJungleMinionsKilled": 0,
  "TotalDamageDealt": 50283,
  "TotalDamageDealtToChampions": 7212,
  "TotalDamageShieldedOnTeammates": 0,
  "TotalDamageTaken": 11435,
  "TotalEnemyJungleMinionsKilled": 0,
  "TotalHeal": 1686,
  "TotalHealsOnTeammates": 258,
  "TotalMinionsKilled": 120,
  "TotalTimeCCDealt": 5,
  "TotalTimeSpentDead": 74,
  "TotalUnitsHealed": 2,
  "TripleKills": 0,
  "TrueDamageDealt": 0,
  "TrueDamageDealtToChampions": 0,
  "TrueDamageTaken": 292,
  "TurretKills": 0,
  "TurretTakedowns": 0,
  "TurretsLost": 8,
  "UnrealKills": 0,
  "VisionClearedPings": 0,
  "VisionScore": 3,
  "VisionWardsBoughtInGame": 0,
  "WardsKilled": 0,
  "WardsPlaced": 3,
  "Win": false,
  "challenge_BlastConeOppositeOpponentCount": 0,
  "endOfGameResult": "GameComplete",
  "gameCreation": 1717390614267,
  "gameDuration": 932,
  "gameEndTimestamp": "2024-06-03 01:12:55",
  "gameId": 5011859685,
  "gameMode": "CLASSIC",
  "gameName": "teambuilder-match-5011859685",
  "gameStartTimestamp": "2024-06-03 00:57:22",
  "gameType": "MATCHED_GAME",
  "gameVersion": "14.11.589.9418",
  "mapId": 11,
  "matchId": "NA1_5011859685",
  "platformId": "NA1"
}
