{
  "AllInPings": 0,
  "AssistMePings": 1,
  "Assists": 7,
  "BaronKills": 0,
  "BasicPings": 0,
  "ChampExperience": 11099,
  "ChampLevel": 13,
  "ChampionID": 143,
  "ChampionName": "Zyra",
  "ChampionTransform": 0,
  "CommandPings": 0,
  "ConsumablesPurchased": 4,
  "DamageDealtToBuildings": 1032,
  "DamageDealtToObjectives": 3642,
  "DamageDealtToTurrets": 1032,
  "DamageSelfMitigated": 8196,
  "DangerPings": 0,
  "Deaths": 7,
  "DetectorWardsPlaced": 1,
  "DoubleKills": 1,
  "DragonKills": 0,
  "EligibleForProgression": true,
  "EnemyMissingPings": 6,
  "EnemyVisionPings": 0,
  "FirstBloodAssist": false,
  "FirstBloodKill": false,
  "FirstTowerAssist": false,
  "FirstTowerKill": false,
  "GameEndedInEarlySurrender": false,
  "GameEndedInSurrender": true,
  "GetBackPings": 0,
  "GoldEarned": 8820,
  "GoldSpent": 8475,
  "HoldPings": 0,
  "IndividualPosition": "MIDDLE",
  "InhibitorKills": 0,
  "InhibitorTakedowns": 0,
  "InhibitorsLost": 1,
  "Item0": 1056,
  "Item1": 6653,
  "Item2": 3020,
  "Item3": 2503,
  "Item4": 3916,
  "Item5": 0,
  "Item6": 3363,
  "ItemsPurchased": 18,
  "KillingSprees": 1,
  "Kills": 3,
  "Lane": "MIDDLE",
  "LargestCriticalStrike": 0,
  "LargestKillingSpree": 2,
  "LargestMultiKill": 2,
  "LongestTimeSpentLiving": 642,
  "MagicDamageDealt": 94347,
  "MagicDamageDealtToChampions": 17317,
  "MagicDamageTaken": 7745,
  "NeedVisionPings": 0,
  "NeutralMinionsKilled": 12,
  "NexusKills": 0,
  "NexusLost": 0,
  "NexusTakedowns": 0,
  "ObjectivesStolen": 0,
  "ObjectivesStolenAssists": 0,
  "OnMyWayPings": 1,
  "ParticipantID": 3,
  "PentaKills": 0,
  "PhysicalDamageDealt": 11254,
  "PhysicalDamageDealtToChampions": 1046,
  "PhysicalDamageTaken": 8677,
  "Placement": 0,
  "PlayerAugment1": 0,
  "PlayerAugment2": 0,
  "PlayerAugment3": 0,
  "PlayerAugment4": 0,
  "PlayerAugment5": 0,
  "PlayerAugment6": 0,
  "PlayerScore0": 0,
  "PlayerScore1": 0,
  "PlayerScore10": 0,
  "PlayerScore11": 0,
  "PlayerScore2": 0,
  "PlayerScore3": 0,
  "PlayerScore4": 0,
  "PlayerScore5": 0,
  "PlayerScore6": 0,
  "PlayerScore7": 0,
  "PlayerScore8": 0,
  "PlayerScore9": 0,
  "PlayerSubteamID": 0,
  "ProfileIcon": 5977,
  "PushPings": 0,
  "Puuid": "TrirJDran-EPeXXJZ0QHOITqvggPOqZqJLwwC1-y-g5_Z99T3DXtHQzLBG8LDGLLaCeZRnOgGraGhg",
  "QuadraKills": 0,
  "RetreatPings": 0,
  "RiotIDGameName": "Taiychi Ud",
  "RiotIDTagline": "NA1",
  "Role": "SOLO",
  "SightWardsBoughtInGame": 0,
  "Spell1Casts": 113,
  "Spell2Casts": 118,
  "Spell3Casts": 33,
  "Spell4Casts": 7,
  "SubteamPlacement": 0,
  "Summoner1Casts": 4,
  "Summoner1ID": 12,
  "Summoner2Casts": 3,
  "Summoner2ID": 4,
  "SummonerID": "dsha2r3-ejOlZP8tMLXLq9nP4VhAD9q1RkozQ5ciBPV0ayU",
  "SummonerLevel": 569,
  "SummonerName": "Taiychi Ud",
  "TeamEarlySurrendered": false,
  "TeamID": 100,
  "TeamPosition": "MIDDLE",
  "TimeCCingOthers": 21,
  "TimePlayed": 1529,
  "TotalAllyJungleMinionsKilled": 6,
  "TotalDamageDealt": 107982,
  "TotalDamageDealtToChampions": 18766,
  "TotalDamageShieldedOnTeammates": 0,
  "TotalDamageTaken": 16975,
  "TotalEnemyJungleMinionsKilled": 0,
  "TotalHeal": 0,
  "TotalHealsOnTeammates": 0,
  "TotalMinionsKilled": 146,
  "TotalTimeCCDealt": 152,
  "TotalTimeSpentDead": 200,
  "TotalUnitsHealed": 0,
  "TripleKills": 0,
  "TrueDamageDealt": 2380,
  "TrueDamageDealtToChampions": 402,
  "TrueDamageTaken": 552,
  "TurretKills": 0,
  "TurretTakedowns": 0,
  "TurretsLost": 5,
  "UnrealKills": 0,
  "VisionClearedPings": 0,
  "VisionScore": 12,
  "VisionWardsBoughtInGame": 1,
  "WardsKilled": 0,
  "WardsPlaced": 8,
  "Win": false,
  "challenge_BlastConeOppositeOpponentCount": 0,
  "endOfGameResult": "GameComplete",
  "gameCreation": 1719799002100,
  "gameDuration": 1529,
  "gameEndTimestamp": "2024-06-30 22:23:52",
  "gameId": 5030690504,
  "gameMode": "CLASSIC",
  "gameName": "teambuilder-match-5030690504",
  "gameStartTimestamp": "2024-06-30 21:58:23",
  "gameType": "MATCHED_GAME",
  "gameVersion": "14.13.596.7996",
  "mapId": 11,
  "matchId": "NA1_5030690504",
  "platformId": "NA1"
}
