{
  "AllInPings": 0,
  "AssistMePings": 5,
  "Assists": 3,
  "BaronKills": 0,
  "BasicPings": 0,
  "ChampExperience": 6958,
  "ChampLevel": 10,
  "ChampionID": 37,
  "ChampionName": "Sona",
  "ChampionTransform": 0,
  "CommandPings": 5,
  "ConsumablesPurchased": 2,
  "DamageDealtToBuildings": 0,
  "DamageDealtToObjectives": 0,
  "DamageDealtToTurrets": 0,
  "DamageSelfMitigated": 4264,
  "DangerPings": 0,
  "Deaths": 0,
  "DetectorWardsPlaced": 0,
  "DoubleKills": 0,
  "DragonKills": 0,
  "EligibleForProgression": true,
  "EnemyMissingPings": 4,
  "EnemyVisionPings": 0,
  "FirstBloodAssist": false,
  "FirstBloodKill": false,
  "FirstTowerAssist": false,
  "FirstTowerKill": false,
  "GameEndedInEarlySurrender": false,
  "GameEndedInSurrender": false,
  "GetBackPings": 1,
  "GoldEarned": 5296,
  "GoldSpent": 5000,
  "HoldPings": 0,
  "IndividualPosition": "UTILITY",
  "InhibitorKills": 0,
  "InhibitorTakedowns": 0,
  "InhibitorsLost": 2,
  "Item0": 6620,
  "Item1": 3009,
  "Item2": 3870,
  "Item3": 4642,
  "Item4": 1028,
  "Item5": 0,
  "Item6": 3364,
  "ItemsPurchased": 15,
  "KillingSprees": 0,
  "Kills": 1,
  "Lane": "BOTTOM",
  "LargestCriticalStrike": 0,
  "LargestKillingSpree": 0,
  "LargestMultiKill": 1,
  "LongestTimeSpentLiving": 0,
  "MagicDamageDealt": 9061,
  "MagicDamageDealtToChampions": 4696,
  "MagicDamageTaken": 3410,
  "NeedVisionPings": 0,
  "NeutralMinionsKilled": 0,
  "NexusKills": 0,
  "NexusLost": 1,
  "NexusTakedowns": 0,
  "ObjectivesStolen": 0,
  "ObjectivesStolenAssists": 0,
  "OnMyWayPings": 6,
  "ParticipantID": 5,
  "PentaKills": 0,
  "PhysicalDamageDealt": 3629,
  "PhysicalDamageDealtToChampions": 1104,
  "PhysicalDamageTaken": 3965,
  "Placement": 0,
  "PlayerAugment1": 0,
  "PlayerAugment2": 0,
  "PlayerAugment3": 0,
  "PlayerAugment4": 0,
  "PlayerAugment5": 0,
  "PlayerAugment6": 0,
  "PlayerScore0": 0,
  "PlayerScore1": 0,
  "PlayerScore10": 0,
  "PlayerScore11": 0,
  "PlayerScore2": 0,
  "PlayerScore3": 0,
  "PlayerScore4": 0,
  "PlayerScore5": 0,
  "PlayerScore6": 0,
  "PlayerScore7": 0,
  "PlayerScore8": 0,
  "PlayerScore9": 0,
  "PlayerSubteamID": 0,
  "ProfileIcon": 19,
  "PushPings": 1,
  "Puuid": "EMyHiwwkJTJXLmgtG1RHS1r6D74pLINM1a4S0ldaUKsiS2mFGiRdRjaBYtev-QyOGgc3Qor0nZrr0A",
  "QuadraKills": 0,
  "RetreatPings": 0,
  "RiotIDGameName": "im sleepy acc",
  "RiotIDTagline": "sleep",
  "Role": "SUPPORT",
  "SightWardsBoughtInGame": 0,
  "Spell1Casts": 40,
  "Spell2Casts": 55,
  "Spell3Casts": 50,
  "Spell4Casts": 3,
  "SubteamPlacement": 0,
  "Summoner1Casts": 3,
  "Summoner1ID": 7,
  "Summoner2Casts": 0,
  "Summoner2ID": 4,
  "SummonerID": "DRqWpELAwgpdH7vlTOvk3g1lSjSo6Fv589IBdMS0130MiV8",
  "SummonerLevel": 435,
  "SummonerName": "buttercup48",
  "TeamEarlySurrendered": false,
  "TeamID": 100,
  "TeamPosition": "UTILITY",
  "TimeCCingOthers": 5,
  "TimePlayed": 1360,
  "TotalAllyJungleMinionsKilled": 0,
  "TotalDamageDealt": 14628,
  "TotalDamageDealtToChampions": 5800,
  "TotalDamageShieldedOnTeammates": 1465,
  "TotalDamageTaken": 7621,
  "TotalEnemyJungleMinionsKilled": 0,
  "TotalHeal": 6623,
  "TotalHealsOnTeammates": 3948,
  "TotalMinionsKilled": 25,
  "TotalTimeCCDealt": 12,
  "TotalTimeSpentDead": 0,
  "TotalUnitsHealed": 5,
  "TripleKills": 0,
  "TrueDamageDealt": 1937,
  "TrueDamageDealtToChampions": 0,
  "TrueDamageTaken": 246,
  "TurretKills": 0,
  "TurretTakedowns": 0,
  "TurretsLost": 10,
  "UnrealKills": 0,
  "VisionClearedPings": 0,
  "VisionScore": 26,
  "VisionWardsBoughtInGame": 0,
  "WardsKilled": 3,
  "WardsPlaced": 11,
  "Win": false,
  "challenge_BlastConeOppositeOpponentCount": 0,
  "endOfGameResult": "GameComplete",
  "gameCreation": 1717564178166,
  "gameDuration": 1360,
  "gameEndTimestamp": "2024-06-05 01:33:15",
  "gameId": 5013266571,
  "gameMode": "CLASSIC",
  "gameName": "teambuilder-match-5013266571",
  "gameStartTimestamp": "2024-06-05 01:10:35",
  "gameType": "MATCHED_GAME",
  "gameVersion": "14.11.589.9418",
  "mapId": 11,
  "matchId": "NA1_5013266571",
  "platformId": "NA1"
}
