{
  "AllInPings": 0,
  "AssistMePings": 2,
  "Assists": 5,
  "BaronKills": 0,
  "BasicPings": 0,
  "ChampExperience": 17087,
  "ChampLevel": 17,
  "ChampionID": 29,
  "ChampionName": "Twitch",
  "ChampionTransform": 0,
  "CommandPings": 2,
  "ConsumablesPurchased": 2,
  "DamageDealtToBuildings": 6347,
  "DamageDealtToObjectives": 10269,
  "DamageDealtToTurrets": 6347,
  "DamageSelfMitigated": 8456,
  "DangerPings": 0,
  "Deaths": 8,
  "DetectorWardsPlaced": 0,
  "DoubleKills": 2,
  "DragonKills": 0,
  "EligibleForProgression": true,
  "EnemyMissingPings": 2,
  "EnemyVisionPings": 0,
  "FirstBloodAssist": false,
  "FirstBloodKill": false,
  "FirstTowerAssist": false,
  "FirstTowerKill": false,
  "GameEndedInEarlySurrender": false,
  "GameEndedInSurrender": false,
  "GetBackPings": 1,
  "GoldEarned": 17828,
  "GoldSpent": 17700,
  "HoldPings": 0,
  "IndividualPosition": "BOTTOM",
  "InhibitorKills": 2,
  "InhibitorTakedowns": 3,
  "InhibitorsLost": 0,
  "Item0": 3006,
  "Item1": 3072,
  "Item2": 3036,
  "Item3": 3085,
  "Item4": 6676,
  "Item5": 3031,
  "Item6": 3363,
  "ItemsPurchased": 27,
  "KillingSprees": 2,
  "Kills": 15,
  "Lane": "BOTTOM",
  "LargestCriticalStrike": 783,
  "LargestKillingSpree": 11,
  "LargestMultiKill": 2,
  "LongestTimeSpentLiving": 798,
  "MagicDamageDealt": 164,
  "MagicDamageDealtToChampions": 0,
  "MagicDamageTaken": 8955,
  "NeedVisionPings": 0,
  "NeutralMinionsKilled": 4,
  "NexusKills": 1,
  "NexusLost": 0,
  "NexusTakedowns": 1,
  "ObjectivesStolen": 0,
  "ObjectivesStolenAssists": 0,
  "OnMyWayPings": 1,
  "ParticipantID": 9,
  "PentaKills": 0,
  "PhysicalDamageDealt": 171133,
  "PhysicalDamageDealtToChampions": 25846,
  "PhysicalDamageTaken": 13278,
  "Placement": 0,
  "PlayerAugment1": 0,
  "PlayerAugment2": 0,
  "PlayerAugment3": 0,
  "PlayerAugment4": 0,
  "PlayerAugment5": 0,
  "PlayerAugment6": 0,
  "PlayerScore0": 0,
  "PlayerScore1": 0,
  "PlayerScore10": 0,
  "PlayerScore11": 0,
  "PlayerScore2": 0,
  "PlayerScore3": 0,
  "PlayerScore4": 0,
  "PlayerScore5": 0,
  "PlayerScore6": 0,
  "PlayerScore7": 0,
  "PlayerScore8": 0,
  "PlayerScore9": 0,
  "PlayerSubteamID": 0,
  "ProfileIcon": 596,
  "PushPings": 0,
  "Puuid": "QfATyyESMEH_V7sUREODipG7U5KjZYUlkjThVRaPOZFVPvmdK1Cf67g5Nyb-suG9f4OoZQfALjnccw",
  "QuadraKills": 0,
  "RetreatPings": 0,
  "RiotIDGameName": "ilovesmarties",
  "RiotIDTagline": "2011",
  "Role": "CARRY",
  "SightWardsBoughtInGame": 0,
  "Spell1Casts": 54,
  "Spell2Casts": 58,
  "Spell3Casts": 41,
  "Spell4Casts": 14,
  "SubteamPlacement": 0,
  "Summoner1Casts": 5,
  "Summoner1ID": 4,
  "Summoner2Casts": 9,
  "Summoner2ID": 6,
  "SummonerID": "wKwHL4aAAT01Sa1pNEtb55yQfEAdmBPM8YU1-BkxPiAMVzk",
  "SummonerLevel": 734,
  "SummonerName": "ilovesmarties",
  "TeamEarlySurrendered": false,
  "TeamID": 200,
  "TeamPosition": "BOTTOM",
  "TimeCCingOthers": 15,
  "TimePlayed": 2088,
  "TotalAllyJungleMinionsKilled": 4,
  "TotalDamageDealt": 193912,
  "TotalDamageDealtToChampions": 30934,
  "TotalDamageShieldedOnTeammates": 0,
  "TotalDamageTaken": 23613,
  "TotalEnemyJungleMinionsKilled": 0,
  "TotalHeal": 3559,
  "TotalHealsOnTeammates": 0,
  "TotalMinionsKilled": 194,
  "TotalTimeCCDealt": 447,
  "TotalTimeSpentDead": 162,
  "TotalUnitsHealed": 1,
  "TripleKills": 0,
  "TrueDamageDealt": 22613,
  "TrueDamageDealtToChampions": 5087,
  "TrueDamageTaken": 1379,
  "TurretKills": 3,
  "TurretTakedowns": 5,
  "TurretsLost": 6,
  "UnrealKills": 0,
  "VisionClearedPings": 0,
  "VisionScore": 13,
  "VisionWardsBoughtInGame": 0,
  "WardsKilled": 2,
  "WardsPlaced": 13,
  "Win": true,
  "challenge_BlastConeOppositeOpponentCount": 0,
  "endOfGameResult": "GameComplete",
  "gameCreation": 1716358716103,
  "gameDuration": 2088,
  "gameEndTimestamp": "2024-05-22 02:54:41",
  "gameId": 5003361711,
  "gameMode": "CLASSIC",
  "gameName": "teambuilder-match-5003361711",
  "gameStartTimestamp": "2024-05-22 02:19:53",
  "gameType": "MATCHED_GAME",
  "gameVersion": "14.10.586.9705",
  "mapId": 11,
  "matchId": "NA1_5003361711",
  "platformId": "NA1"
}
